{
  "parent": "minecraft:recipes/root",
  "rewards": {
    "recipes": [
      "minitect:materials/aluminum_steel/smelting/ingot_from_dust"
    ]
  },
  "criteria": {
    "has_item": {
      "trigger": "minecraft:inventory_changed",
      "conditions": {
        "items": [
          {
            "tag": "forge:dusts/aluminum_steel"
          }
        ]
      }
    },
    "has_the_recipe": {
      "trigger": "minecraft:recipe_unlocked",
      "conditions": {
        "recipe": "minitect:materials/aluminum_steel/smelting/ingot_from_dust"
      }
    }
  },
  "requirements": [
    [
      "has_item",
      "has_the_recipe"
    ]
  ]
}